{"final_samples":{"_type":"image-file","sha256":"61456d580235bb84930cd792c5cbc55a11cca086621fe9b5428ced4f8e98f885","size":10320,"path":"media/images/final_samples_50_61456d580235bb84930c.png","format":"png","width":122,"height":122,"caption":"Epoch 50"},"best_model_path":"saved_models/diffusion/diffusion_VADAM_uzopj79d_best.pt","_timestamp":1.7472373803766153e+09,"val_loss":0.038923500383153876,"epoch":50,"_step":50,"train_time":6907.531286478043,"_runtime":6908.585142909,"final_train_loss":0.039406866532578286,"samples":{"height":122,"caption":"Epoch 50","_type":"image-file","sha256":"d44c6e8b01d17775d0c9154fa0ac8b0bd70a12b8feb8c2007b2d79bd3efa82d5","size":10383,"path":"media/images/samples_49_d44c6e8b01d17775d0c9.png","format":"png","width":122},"train_loss":0.039406866532578286,"_wandb":{"runtime":6908},"test_loss":0.03870983379362505,"final_val_loss":0.038923500383153876,"best_val_loss":0.03859085668908789}